cmder/__init__.py
cmder/cmder.py
cmder-5.0.dist-info/LICENSE
cmder-5.0.dist-info/METADATA
cmder-5.0.dist-info/WHEEL
cmder-5.0.dist-info/top_level.txt
cmder-5.0.dist-info/RECORD
