Metadata-Version: 2.1
Name: cmder
Version: 5.0
Summary: A shortcut for running shell command.
Home-page: https://github.com/iBiology/cmder.git
Author: FEI YUAN
Author-email: yuanfeifuzzy@gmail.com
Project-URL: Bug Tracker, https://github.com/pypa/sampleproject/issues
Classifier: Programming Language :: Python :: 3
Classifier: License :: OSI Approved :: MIT License
Classifier: Operating System :: POSIX
Requires-Python: >=3.6
License-File: LICENSE
